xrypt_xethhung12/rsa_encryption/__init__.py
xrypt_xethhung12/rsa_encryption/rsa_encryption.py
xrypt_xethhung12/rsa_format/__init__.py
xrypt_xethhung12/rsa_format/rsa_format.py
xrypt_xethhung12/xrypt/__init__.py
xrypt_xethhung12/xrypt/xrypt.py
xrypt_xethhung12-0.0.10.dist-info/METADATA
xrypt_xethhung12-0.0.10.dist-info/WHEEL
xrypt_xethhung12-0.0.10.dist-info/top_level.txt
xrypt_xethhung12-0.0.10.dist-info/RECORD
