Metadata-Version: 2.1
Name: xrypt-xethhung12
Version: 0.0.10
Summary: A simple tools to hybrid encryption and decryption
Author-email: Xeth Hung <admin@xethh.me>
Project-URL: Homepage, https://github.com/xh-dev-py/xrypt-xethhung12
Project-URL: Bug Tracker, https://github.com/xh-dev-py/xrypt-xethhung12/issues
Classifier: Programming Language :: Python :: 3
Classifier: License :: OSI Approved :: MIT License
Classifier: Operating System :: OS Independent
Requires-Python: >=3.7
Requires-Dist: crypto
Requires-Dist: cryptography
Requires-Dist: pycryptodome
